early_stopping_pytorch/__init__.py
early_stopping_pytorch/early_stopping.py
early_stopping_pytorch-1.0.10.dist-info/LICENSE
early_stopping_pytorch-1.0.10.dist-info/METADATA
early_stopping_pytorch-1.0.10.dist-info/WHEEL
early_stopping_pytorch-1.0.10.dist-info/top_level.txt
early_stopping_pytorch-1.0.10.dist-info/RECORD
