Metadata-Version: 2.1
Name: early-stopping-pytorch
Version: 1.0.10
Summary: A PyTorch utility package for Early Stopping
Author-email: Bjarte Mehus Sunde <BjarteSunde@outlook.com>
License: MIT
Project-URL: Repository, https://github.com/Bjarten/early-stopping-pytorch
License-File: LICENSE
Requires-Dist: numpy>=1.21
Requires-Dist: torch>=1.9.0
